copycatm/__init__.py
copycatm/__main__.py
copycatm/analysis/__init__.py
copycatm/analysis/algorithm_detector.py
copycatm/analysis/algorithm_detector_enhanced_final.py
copycatm/analysis/algorithm_types.py
copycatm/analysis/algorithmic_normalizer.py
copycatm/analysis/ast_algorithm_detector.py
copycatm/analysis/ast_normalizer.py
copycatm/analysis/call_graph.py
copycatm/analysis/code_clone_detector.py
copycatm/analysis/coherence_validator.py
copycatm/analysis/complexity.py
copycatm/analysis/confidence_scorer.py
copycatm/analysis/control_block_extractor.py
copycatm/analysis/cross_language_normalizer.py
copycatm/analysis/dependency_extractor.py
copycatm/analysis/directory_structure.py
copycatm/analysis/false_positive_filter.py
copycatm/analysis/invariant_extractor.py
copycatm/analysis/invariant_extractor_improved.py
copycatm/analysis/mathematical_invariance.py
copycatm/analysis/mathematical_property_detector.py
copycatm/analysis/metadata.py
copycatm/analysis/mutation_detector.py
copycatm/analysis/pattern_loader.py
copycatm/analysis/pseudocode_normalizer.py
copycatm/analysis/semantic_similarity.py
copycatm/analysis/structural_complexity.py
copycatm/analysis/transformation_resistance_calculator.py
copycatm/analysis/unknown_algorithm_clustering.py
copycatm/analysis/unknown_algorithm_detector.py
copycatm/analysis/wrapper_detector.py
copycatm/cli/__init__.py
copycatm/cli/commands.py
copycatm/cli/utils.py
copycatm/core/__init__.py
copycatm/core/advanced_config.py
copycatm/core/analyzer.py
copycatm/core/config.py
copycatm/core/config_improvements_v2.py
copycatm/core/exceptions.py
copycatm/core/signature_aggregator.py
copycatm/core/swhid.py
copycatm/core/three_tier_analyzer.py
copycatm/data/__init__.py
copycatm/data/algorithm_patterns.py
copycatm/data/language_configs.py
copycatm/gnn/__init__.py
copycatm/gnn/gnn_model.py
copycatm/gnn/graph_builder.py
copycatm/gnn/semantic_graph_builder.py
copycatm/gnn/similarity_detector.py
copycatm/hashing/__init__.py
semantic_copycat_minner-1.5.4.dist-info/licenses/LICENSE
semantic_copycat_minner-1.5.4.dist-info/METADATA
semantic_copycat_minner-1.5.4.dist-info/WHEEL
semantic_copycat_minner-1.5.4.dist-info/entry_points.txt
semantic_copycat_minner-1.5.4.dist-info/top_level.txt
semantic_copycat_minner-1.5.4.dist-info/RECORD
