Metadata-Version: 2.4
Name: semantic-copycat-minner
Version: 1.5.4
Summary: Semantic analysis tool for detecting AI-generated code derived from copyrighted sources
Author-email: "Oscar Valenzuela B." <oscar.valenzuela.b@gmail.com>
Maintainer-email: "Oscar Valenzuela B." <oscar.valenzuela.b@gmail.com>
License: AGPL-3.0
Project-URL: Homepage, https://github.com/oscarvalenzuelab/semantic-copycat-minner
Project-URL: Documentation, https://github.com/oscarvalenzuelab/semantic-copycat-minner#readme
Project-URL: Repository, https://github.com/oscarvalenzuelab/semantic-copycat-minner
Project-URL: Bug Tracker, https://github.com/oscarvalenzuelab/semantic-copycat-minner/issues
Keywords: code-analysis,ai-detection,semantic-analysis,copyright,gpl
Classifier: Development Status :: 4 - Beta
Classifier: Intended Audience :: Developers
Classifier: License :: OSI Approved :: GNU Affero General Public License v3
Classifier: Programming Language :: Python :: 3
Classifier: Programming Language :: Python :: 3.8
Classifier: Programming Language :: Python :: 3.9
Classifier: Programming Language :: Python :: 3.10
Classifier: Programming Language :: Python :: 3.11
Classifier: Programming Language :: Python :: 3.12
Classifier: Topic :: Software Development :: Libraries :: Python Modules
Classifier: Topic :: Software Development :: Quality Assurance
Requires-Python: >=3.8
License-File: LICENSE
Requires-Dist: tree-sitter>=0.20.0
Requires-Dist: tree-sitter-python>=0.20.0
Requires-Dist: tree-sitter-javascript>=0.20.0
Requires-Dist: tree-sitter-java>=0.20.0
Requires-Dist: tree-sitter-c>=0.20.0
Requires-Dist: tree-sitter-go>=0.20.0
Requires-Dist: tree-sitter-rust>=0.20.0
Requires-Dist: tlsh>=0.2.0
Requires-Dist: datasketch>=1.5.0
Requires-Dist: click>=8.0.0
Requires-Dist: tqdm>=4.64.0
Requires-Dist: python-magic>=0.4.27
Requires-Dist: radon>=5.1.0
Requires-Dist: networkx>=2.8
Provides-Extra: dev
Requires-Dist: pytest>=7.0.0; extra == "dev"
Requires-Dist: black>=22.0.0; extra == "dev"
Requires-Dist: flake8>=5.0.0; extra == "dev"
Requires-Dist: mypy>=0.991; extra == "dev"
Provides-Extra: gnn
Requires-Dist: torch>=1.12.0; extra == "gnn"
Requires-Dist: torch-geometric>=2.1.0; extra == "gnn"
Dynamic: license-file
